letme/__init__.py
letme/auth.py
letme/config.py
letme/core.py
letme/gui.py
letme/helpers.py
letme-1.0.dist-info/LICENSE
letme-1.0.dist-info/METADATA
letme-1.0.dist-info/WHEEL
letme-1.0.dist-info/top_level.txt
letme-1.0.dist-info/RECORD
