Metadata-Version: 2.1
Name: letme
Version: 1.0
Summary: A package to simplify working with Delta Lake and Spark-SQL
Author: hamodirtyeza
Author-email: hamodirtyeza97@gmail.com
Requires-Python: >=3.12
License-File: LICENSE
